{
  "products": [
    {
      "id": "1",
      "name": "Men'S Anime Cartoon Print Hooded Sweatshirt",
      "price": 20,
      "imgUrl": [
        "/item1.jpg",
        "/item1.jpg",
        "/item1.jpg",
        "/item2.jpg"
      ],
      "type": "men"
    },
    {
      "id": "2",
      "name": "Men's Casual Black T-Shirt with Unique Anime",
      "price": 10,
      "imgUrl": [
        "/item2.jpg",
        "/item2.jpg",
        "/item2.jpg",
        "/item3.jpg"
      ],
      "type": "men"
    },
    {
      "id": "3",
      "name": "Casual Anime Graphic Hooded Sweatshirt",
      "price": 15,
      "imgUrl": [
        "/item3.jpg",
        "/item3.jpg",
        "/item3.jpg",
        "/item4.jpg"
      ],
      "type": "men"
    },
    {
      "id": "4",
      "name": "Casual Anime Graphic Hooded Sweatshirt",
      "price": 25,
      "imgUrl": [
        "/item4.jpg",
        "/item4.jpg",
        "/item4.jpg",
        "/item5.jpg"
      ],
      "type": "kids"
    },
    {
      "id": "5",
      "name": "Boys' Pink Anime-Inspired Hoodie",
      "price": 20,
      "imgUrl": [
        "/item5.jpg",
        "/item5.jpg",
        "/item5.jpg",
        "/item6.jpg"
      ],
      "type": "kids"
    },
    {
      "id": "6",
      "name": "Girls' Summer Comfort Tee - Casual",
      "price": 10,
      "imgUrl": [
        "/item6.jpg",
        "/item6.jpg",
        "/item6.jpg",
        "/item7.jpg"
      ],
      "type": "women"
    },
    {
      "id": "7",
      "name": "Girls' Summer Comfort Tee - Casual",
      "price": 15,
      "imgUrl": [
        "/item7.jpg",
        "/item7.jpg",
        "/item7.jpg",
        "/item8.jpg"
      ],
      "type": "women"
    },
    {
      "id": "8",
      "name": "Girls' Casual Short Sleeve T-shirt",
      "price": 25,
      "imgUrl": [
        "/item8.jpg",
        "/item8.jpg",
        "/item8.jpg",
        "/item1.jpg"
      ],
      "type": "women"
    }
  ],
  "basket": [],
  "order": [
    {
      "0": {
        "id": "7f01",
        "name": "Casual Anime Graphic Hooded Sweatshirt",
        "price": 15,
        "imgUrl": [
          "/item3.jpg",
          "/item3.jpg",
          "/item3.jpg",
          "/item4.jpg"
        ],
        "type": "men",
        "productId": "3",
        "count": 1
      },
      "id": "51c9"
    }
  ]
}